indentgen/__init__.py
indentgen/endpoints.py
indentgen/img_resize_utils.py
indentgen/indentgen.py
indentgen/page_store.py
indentgen/paginator.py
indentgen/path_dict.py
indentgen/taxonomy_def_set.py
indentgen/wisdom.py
indentgen/default_definitions/__init__.py
indentgen/default_definitions/config_tag_defs.py
indentgen/default_definitions/content_tag_defs.py
indentgen/default_definitions/taxonomy_tag_defs.py
indentgen-0.0.3.data/scripts/indentgen
indentgen-0.0.3.dist-info/LICENSE
indentgen-0.0.3.dist-info/METADATA
indentgen-0.0.3.dist-info/WHEEL
indentgen-0.0.3.dist-info/top_level.txt
indentgen-0.0.3.dist-info/RECORD
