Metadata-Version: 2.1
Name: indentgen
Version: 0.0.3
Summary: A static site generator for Dentmark
Home-page: https://www.transvec.com/indentgen
Author: Ryli Dunlap
Author-email: ryli@transvec.com
License: UNKNOWN
Platform: UNKNOWN
Classifier: Programming Language :: Python :: 3
Classifier: License :: OSI Approved :: GNU General Public License v3 (GPLv3)
Classifier: Operating System :: OS Independent
Requires-Python: >=3.6
Requires-Dist: dentmark
Requires-Dist: mako
Requires-Dist: Pillow
